chartcoach/__init__.py
chartcoach-0.1.0.dist-info/WHEEL
chartcoach-0.1.0.dist-info/entry_points.txt
chartcoach-0.1.0.dist-info/METADATA
chartcoach-0.1.0.dist-info/RECORD
