Metadata-Version: 2.3
Name: chartcoach
Version: 0.1.0
Summary: WIP
Author: Péter Ferenc Gyarmati
Author-email: Péter Ferenc Gyarmati <dev.petergy@gmail.com>
Requires-Python: >=3.12
